AUTHORS.rst
CHANGELOG.rst
LICENSE
MANIFEST.in
README.rst
setup.py
competition/__init__.py
competition/admin.py
competition/forms.py
competition/generator.py
competition/models.py
competition/test_urls.py
competition/tests.py
competition/urls.py
competition/views.py
competition/migrations/0001_initial.py
competition/migrations/0001_initial.pyc
competition/migrations/0002_auto__add_competitionansweroption__del_field_competitionentry_answer__.py
competition/migrations/0002_auto__add_competitionansweroption__del_field_competitionentry_answer__.pyc
competition/migrations/0003_auto__add_field_competition_check_in_distance__add_field_competition_a.py
competition/migrations/0003_auto__add_field_competition_check_in_distance__add_field_competition_a.pyc
competition/migrations/__init__.py
competition/migrations/__init__.pyc
competition/templates/admin/competition/competitionentry/change_list.html
competition/templates/basic/competition/competition_detail.html
competition/templates/basic/competition/competition_terms.html
competition/templates/basic/competition/inclusion_tags/competition_detail.html
competition/templates/smart/competition/inclusion_tags/competition_detail.html
competition/templatetags/__init__.py
competition/templatetags/__init__.pyc
competition/templatetags/competition_tags.py
competition/templatetags/competition_tags.pyc
jmbo_competition.egg-info/PKG-INFO
jmbo_competition.egg-info/SOURCES.txt
jmbo_competition.egg-info/dependency_links.txt
jmbo_competition.egg-info/not-zip-safe
jmbo_competition.egg-info/requires.txt
jmbo_competition.egg-info/top_level.txt