Metadata-Version: 1.1
Name: jmbo-competition
Version: 0.1.8
Summary: Jmbo competition app.
Home-page: http://github.com/praekelt/jmbo-competition
Author: Praekelt International
Author-email: dev@praekelt.com
License: BSD
Platform: UNKNOWN
Classifier: Programming Language :: Python
Classifier: License :: OSI Approved :: BSD License
Classifier: Development Status :: 4 - Beta
Classifier: Operating System :: OS Independent
Classifier: Framework :: Django
Classifier: Intended Audience :: Developers
Classifier: Topic :: Internet :: WWW/HTTP :: Dynamic Content
